MANIFEST.in
README.rst
setup.cfg
setup.py
zibal/__init__.py
zibal/admin.py
zibal/apps.py
zibal/models.py
zibal/tests.py
zibal/urls.py
zibal/utils.py
zibal/views.py
zibal/zb.py
zibal/migrations/0001_initial.py
zibal/migrations/__init__.py
zibal_django.egg-info/PKG-INFO
zibal_django.egg-info/SOURCES.txt
zibal_django.egg-info/dependency_links.txt
zibal_django.egg-info/top_level.txt